krawl/__init__.py
krawl/api/pagecontent.py
krawl/api/search.py
krawl/common/__init__.py
krawl/common/config/globals.py
krawl/common/data/dummies/no_title.html
krawl/common/data/dummies/tiny.html
krawl/common/decorators/basics.py
krawl/common/flow/__init__.py
krawl/common/flow/base_pipeline.py
krawl/common/recognizers/__init__.py
krawl/common/recognizers/base_recognizer.py
krawl/common/recognizers/content_recognizer.py
krawl/common/recognizers/soup_extractor.py
krawl/common/schema/dtypes.py
krawl/common/soup_utils/__init__.py
krawl/common/soup_utils/context.py
krawl/common/soup_utils/page_reader.py
krawl/common/soup_utils/texttools.py
krawl/common/soup_utils/urlcheck.py
krawl/common/textware/__init__.py
krawl/common/textware/textfilter.py
krawl/common/url_utils/__init__.py
krawl/expert_crawler/__init__.py
krawl/expert_crawler/company_crawler/__init__.py
krawl/expert_crawler/company_crawler/crawler/homepage_crawler.py
krawl/expert_crawler/company_crawler/ml_models/dataset.py
krawl/expert_crawler/company_crawler/ml_models/dtypes.py
krawl/expert_crawler/company_crawler/ml_models/eval.py
krawl/expert_crawler/company_crawler/ml_models/predict.py
krawl/expert_crawler/company_crawler/ml_models/train.py
krawl/expert_crawler/company_crawler/ml_models/train_not_using_pd.py
krawl/expert_crawler/company_crawler/ml_models/training_data/labelled_data_classififer.py
krawl/expert_crawler/company_crawler/ml_models/workflow.py
krawl/expert_crawler/company_crawler/predictors/__init__.py
krawl/expert_crawler/company_crawler/predictors/base_clf.py
krawl/expert_crawler/company_crawler/predictors/model_io.py
krawl/expert_crawler/company_crawler/predictors/node_predictors.py
krawl/expert_crawler/company_crawler/recognizers/__init__.py
krawl/expert_crawler/company_crawler/recognizers/title_recognizer.py
krawl/expert_crawler/company_crawler/schema/dtypes.py
krawl/expert_crawler/generic_crawler/__init__.py
krawl/expert_crawler/generic_crawler/crawler/content_crawler.py
krawl-0.0.6.dist-info/METADATA
krawl-0.0.6.dist-info/WHEEL
krawl-0.0.6.dist-info/RECORD
