Metadata-Version: 2.1
Name: krawl
Version: 0.0.6
Summary: Krawl: A collection of crawlers
License: BSD
Author: Kun Lu
Author-email: hi@shugic.com
Requires-Python: >=3.9,<4.0
Classifier: License :: Other/Proprietary License
Classifier: Programming Language :: Python :: 3
Classifier: Programming Language :: Python :: 3.9
Classifier: Programming Language :: Python :: 3.10
Classifier: Programming Language :: Python :: 3.11
Classifier: Programming Language :: Python :: 3.12
Requires-Dist: aiohttp[speedups] (>=3.10.8,<4.0.0)
Requires-Dist: beautifulsoup4 (>=4.12.2,<5.0.0)
Requires-Dist: duckduckgo-search (>=6.2.11,<7.0.0)
Requires-Dist: fire (>=0.5.0,<0.6.0)
Requires-Dist: jsonlines (>=4.0.0,<5.0.0)
Requires-Dist: jsonpickle (>=3.0.2,<4.0.0)
Requires-Dist: numpy (>=1.25.0,<2.0.0) ; python_version >= "3.9" and python_version < "3.13"
Requires-Dist: pandas (>=2.1.0,<3.0.0)
Requires-Dist: pydantic (>=2.3.0,<3.0.0)
Requires-Dist: pyyaml (>=6.0.1,<7.0.0)
Requires-Dist: requests (>=2.31.0,<3.0.0)
Requires-Dist: retrying (>=1.3.4,<2.0.0)
Requires-Dist: scikit-learn (>=1.3.2,<2.0.0)
Requires-Dist: selenium (>=4.15.2,<5.0.0)
Requires-Dist: tldextract (>=5.1.2,<6.0.0)
Requires-Dist: webdriver-manager (>=4.0.1,<5.0.0)
